smtpfixture
