Metadata-Version: 1.1
Name: smtpfixture
Version: 0.4
Summary: SMTP Server that keep all email
Home-page: UNKNOWN
Author: Guillaume Gauvrit
Author-email: guillaume@gauvr.it
License: UNKNOWN
Platform: UNKNOWN
Classifier: Programming Language :: Python
Classifier: Programming Language :: Python :: 2.7
Classifier: License :: OSI Approved :: BSD License
